{
  "meta": {
    "record_id": "nsw_legislation:2022-11-25/act-1997-078_part_1_division_1_section_3",
    "text_hash": "ec13989ea4742ba1d8ad9aaaa8ea15d5",
    "text": "Definitions In this Act— Aboriginal means a person who— (a) is a member of the Aboriginal race of Australia, and (b) identifies as an Aboriginal, and (c) is accepted by the Aboriginal community as an Aboriginal. Aboriginal child means a child of an Aboriginal. approved person means a person chosen from a list of persons designated by the Director-General of the Department of Community Services under section 24. area has the same meaning as it has in the Local Government Act 1993 and includes part of an area. care residence of a person means the place where the person resides under the care or in the custody of a carer. carer of a person means any person who has residential care and control of a child under out-of-home care arrangements made under the Children and Young Persons (Care and Protection) Act 1998. child means a person who is under the age of 18 years. council has the same meaning as it has in the Local Government Act 1993. court means a court exercising criminal jurisdiction. crime prevention includes, but is not limited to, strategies, initiatives and services that are likely to develop or enhance a safer community. cultural heritage includes beliefs, morals, laws, customs, religion, superstitions, art, language, diet, dress and race. Department means the Attorney General's Department. exercise a function includes perform a duty. function includes a power, authority or duty. local crime prevention plan means a local crime prevention plan adopted by a council under Part 4 and in force in relation to an area. operational area means an area in respect of which a declaration under section 14 is in force. parent of a child includes— (a) a guardian of the child, and (b) a person who has custody of the child, but does not include the Minister administering the Children and Young Persons (Care and Protection) Act 1998 or the Director-General of the Department of Community Services, or the father or mother of the child if the father or mother has neither guardianship nor custody of the child. public place means— (a) a place (whether or not covered by water), or (b) a part of premises, that is open to the public, or is used by the public, whether or not on payment of money or other consideration, whether or not it is ordinarily so open or used and whether or not the public to whom it is open consists of only a limited class of persons. safer community compact—see section 39. Torres Strait Islander means a descendant of an indigenous inhabitant of the Torres Strait Islands. Torres Strait Islander child means a child of a Torres Strait Islander.",
    "token_count": 539,
    "char_count": 2591,
    "graph_stats": {
      "total_nodes": 21,
      "llm_extracted_nodes": 20,
      "total_relationships": 22,
      "llm_extracted_relationships": 2,
      "mentions_relationships": 20
    }
  },
  "nodes": [
    {
      "id": "nsw_legislation:2022-11-25/act-1997-078_part_1_division_1_section_3",
      "type": "ENTITY",
      "properties": {
        "name": "nsw_legislation:2022-11-25/act-1997-078_part_1_division_1_section_3",
        "discourse_role": "SECTION"
      }
    },
    {
      "id": "Aboriginal",
      "type": "Entity",
      "properties": {
        "name": "Aboriginal",
        "discourse_role": "DEFINITION",
        "definition": "a person who— (a) is a member of the Aboriginal race of Australia, and (b) identifies as an Aboriginal, and (c) is accepted by the Aboriginal community as an Aboriginal."
      }
    },
    {
      "id": "Aboriginal Child",
      "type": "Entity",
      "properties": {
        "name": "Aboriginal child",
        "discourse_role": "DEFINITION",
        "definition": "a child of an Aboriginal."
      }
    },
    {
      "id": "Approved Person",
      "type": "Entity",
      "properties": {
        "name": "approved person",
        "discourse_role": "DEFINITION",
        "definition": "a person chosen from a list of persons designated by the Director-General of the Department of Community Services under section 24."
      }
    },
    {
      "id": "Area",
      "type": "Entity",
      "properties": {
        "name": "area",
        "discourse_role": "DEFINITION",
        "definition": "the same meaning as it has in the Local Government Act 1993 and includes part of an area."
      }
    },
    {
      "id": "Care Residence Of A Person",
      "type": "Entity",
      "properties": {
        "name": "care residence of a person",
        "discourse_role": "DEFINITION",
        "definition": "the place where the person resides under the care or in the custody of a carer."
      }
    },
    {
      "id": "Carer Of A Person",
      "type": "Entity",
      "properties": {
        "name": "carer of a person",
        "discourse_role": "DEFINITION",
        "definition": "any person who has residential care and control of a child under out-of-home care arrangements made under the Children and Young Persons (Care and Protection) Act 1998."
      }
    },
    {
      "id": "Child",
      "type": "Entity",
      "properties": {
        "name": "child",
        "discourse_role": "DEFINITION",
        "definition": "a person who is under the age of 18 years."
      }
    },
    {
      "id": "Council",
      "type": "Entity",
      "properties": {
        "name": "council",
        "discourse_role": "DEFINITION",
        "definition": "the same meaning as it has in the Local Government Act 1993."
      }
    },
    {
      "id": "Court",
      "type": "Entity",
      "properties": {
        "name": "court",
        "discourse_role": "DEFINITION",
        "definition": "a court exercising criminal jurisdiction."
      }
    },
    {
      "id": "Crime Prevention",
      "type": "Entity",
      "properties": {
        "name": "crime prevention",
        "discourse_role": "DEFINITION",
        "definition": "strategies, initiatives and services that are likely to develop or enhance a safer community."
      }
    },
    {
      "id": "Cultural Heritage",
      "type": "Entity",
      "properties": {
        "name": "cultural heritage",
        "discourse_role": "DEFINITION",
        "definition": "beliefs, morals, laws, customs, religion, superstitions, art, language, diet, dress and race."
      }
    },
    {
      "id": "Department",
      "type": "Entity",
      "properties": {
        "name": "Department",
        "discourse_role": "DEFINITION",
        "definition": "the Attorney General's Department."
      }
    },
    {
      "id": "Exercise A Function",
      "type": "Entity",
      "properties": {
        "name": "exercise a function",
        "discourse_role": "DEFINITION",
        "definition": "perform a duty."
      }
    },
    {
      "id": "Function",
      "type": "Entity",
      "properties": {
        "name": "function",
        "discourse_role": "DEFINITION",
        "definition": "a power, authority or duty."
      }
    },
    {
      "id": "Local Crime Prevention Plan",
      "type": "Entity",
      "properties": {
        "name": "local crime prevention plan",
        "discourse_role": "DEFINITION",
        "definition": "a local crime prevention plan adopted by a council under Part 4 and in force in relation to an area."
      }
    },
    {
      "id": "Operational Area",
      "type": "Entity",
      "properties": {
        "name": "operational area",
        "discourse_role": "DEFINITION",
        "definition": "an area in respect of which a declaration under section 14 is in force."
      }
    },
    {
      "id": "Parent Of A Child",
      "type": "Entity",
      "properties": {
        "name": "parent of a child",
        "discourse_role": "DEFINITION",
        "definition": "(a) a guardian of the child, and (b) a person who has custody of the child, but does not include the Minister administering the Children and Young Persons (Care and Protection) Act 1998 or the Director-General of the Department of Community Services, or the father or mother of the child if the father or mother has neither guardianship nor custody of the child."
      }
    },
    {
      "id": "Public Place",
      "type": "Entity",
      "properties": {
        "name": "public place",
        "discourse_role": "DEFINITION",
        "definition": "(a) a place (whether or not covered by water), or (b) a part of premises, that is open to the public, or is used by the public, whether or not on payment of money or other consideration, whether or not it is ordinarily so open or used and whether or not the public to whom it is open consists of only a limited class of persons."
      }
    },
    {
      "id": "Torres Strait Islander",
      "type": "Entity",
      "properties": {
        "name": "Torres Strait Islander",
        "discourse_role": "DEFINITION",
        "definition": "a descendant of an indigenous inhabitant of the Torres Strait Islands."
      }
    },
    {
      "id": "Torres Strait Islander Child",
      "type": "Entity",
      "properties": {
        "name": "Torres Strait Islander child",
        "discourse_role": "DEFINITION",
        "definition": "a child of a Torres Strait Islander."
      }
    }
  ],
  "relationships": [
    {
      "source_id": "Aboriginal",
      "source_type": "Entity",
      "type": "DEFINES",
      "target_id": "Aboriginal Child",
      "target_type": "Entity",
      "properties": {}
    },
    {
      "source_id": "Torres Strait Islander",
      "source_type": "Entity",
      "type": "DEFINES",
      "target_id": "Torres Strait Islander Child",
      "target_type": "Entity",
      "properties": {}
    },
    {
      "source_id": "nsw_legislation:2022-11-25/act-1997-078_part_1_division_1_section_3",
      "source_type": "ENTITY",
      "type": "MENTIONS",
      "target_id": "Aboriginal",
      "target_type": "ENTITY",
      "properties": {}
    },
    {
      "source_id": "nsw_legislation:2022-11-25/act-1997-078_part_1_division_1_section_3",
      "source_type": "ENTITY",
      "type": "MENTIONS",
      "target_id": "Aboriginal Child",
      "target_type": "ENTITY",
      "properties": {}
    },
    {
      "source_id": "nsw_legislation:2022-11-25/act-1997-078_part_1_division_1_section_3",
      "source_type": "ENTITY",
      "type": "MENTIONS",
      "target_id": "Approved Person",
      "target_type": "ENTITY",
      "properties": {}
    },
    {
      "source_id": "nsw_legislation:2022-11-25/act-1997-078_part_1_division_1_section_3",
      "source_type": "ENTITY",
      "type": "MENTIONS",
      "target_id": "Area",
      "target_type": "ENTITY",
      "properties": {}
    },
    {
      "source_id": "nsw_legislation:2022-11-25/act-1997-078_part_1_division_1_section_3",
      "source_type": "ENTITY",
      "type": "MENTIONS",
      "target_id": "Care Residence Of A Person",
      "target_type": "ENTITY",
      "properties": {}
    },
    {
      "source_id": "nsw_legislation:2022-11-25/act-1997-078_part_1_division_1_section_3",
      "source_type": "ENTITY",
      "type": "MENTIONS",
      "target_id": "Carer Of A Person",
      "target_type": "ENTITY",
      "properties": {}
    },
    {
      "source_id": "nsw_legislation:2022-11-25/act-1997-078_part_1_division_1_section_3",
      "source_type": "ENTITY",
      "type": "MENTIONS",
      "target_id": "Child",
      "target_type": "ENTITY",
      "properties": {}
    },
    {
      "source_id": "nsw_legislation:2022-11-25/act-1997-078_part_1_division_1_section_3",
      "source_type": "ENTITY",
      "type": "MENTIONS",
      "target_id": "Council",
      "target_type": "ENTITY",
      "properties": {}
    },
    {
      "source_id": "nsw_legislation:2022-11-25/act-1997-078_part_1_division_1_section_3",
      "source_type": "ENTITY",
      "type": "MENTIONS",
      "target_id": "Court",
      "target_type": "ENTITY",
      "properties": {}
    },
    {
      "source_id": "nsw_legislation:2022-11-25/act-1997-078_part_1_division_1_section_3",
      "source_type": "ENTITY",
      "type": "MENTIONS",
      "target_id": "Crime Prevention",
      "target_type": "ENTITY",
      "properties": {}
    },
    {
      "source_id": "nsw_legislation:2022-11-25/act-1997-078_part_1_division_1_section_3",
      "source_type": "ENTITY",
      "type": "MENTIONS",
      "target_id": "Cultural Heritage",
      "target_type": "ENTITY",
      "properties": {}
    },
    {
      "source_id": "nsw_legislation:2022-11-25/act-1997-078_part_1_division_1_section_3",
      "source_type": "ENTITY",
      "type": "MENTIONS",
      "target_id": "Department",
      "target_type": "ENTITY",
      "properties": {}
    },
    {
      "source_id": "nsw_legislation:2022-11-25/act-1997-078_part_1_division_1_section_3",
      "source_type": "ENTITY",
      "type": "MENTIONS",
      "target_id": "Exercise A Function",
      "target_type": "ENTITY",
      "properties": {}
    },
    {
      "source_id": "nsw_legislation:2022-11-25/act-1997-078_part_1_division_1_section_3",
      "source_type": "ENTITY",
      "type": "MENTIONS",
      "target_id": "Function",
      "target_type": "ENTITY",
      "properties": {}
    },
    {
      "source_id": "nsw_legislation:2022-11-25/act-1997-078_part_1_division_1_section_3",
      "source_type": "ENTITY",
      "type": "MENTIONS",
      "target_id": "Local Crime Prevention Plan",
      "target_type": "ENTITY",
      "properties": {}
    },
    {
      "source_id": "nsw_legislation:2022-11-25/act-1997-078_part_1_division_1_section_3",
      "source_type": "ENTITY",
      "type": "MENTIONS",
      "target_id": "Operational Area",
      "target_type": "ENTITY",
      "properties": {}
    },
    {
      "source_id": "nsw_legislation:2022-11-25/act-1997-078_part_1_division_1_section_3",
      "source_type": "ENTITY",
      "type": "MENTIONS",
      "target_id": "Parent Of A Child",
      "target_type": "ENTITY",
      "properties": {}
    },
    {
      "source_id": "nsw_legislation:2022-11-25/act-1997-078_part_1_division_1_section_3",
      "source_type": "ENTITY",
      "type": "MENTIONS",
      "target_id": "Public Place",
      "target_type": "ENTITY",
      "properties": {}
    },
    {
      "source_id": "nsw_legislation:2022-11-25/act-1997-078_part_1_division_1_section_3",
      "source_type": "ENTITY",
      "type": "MENTIONS",
      "target_id": "Torres Strait Islander",
      "target_type": "ENTITY",
      "properties": {}
    },
    {
      "source_id": "nsw_legislation:2022-11-25/act-1997-078_part_1_division_1_section_3",
      "source_type": "ENTITY",
      "type": "MENTIONS",
      "target_id": "Torres Strait Islander Child",
      "target_type": "ENTITY",
      "properties": {}
    }
  ]
}